backy2
