Metadata-Version: 1.1
Name: backy2
Version: 2.9.16
Summary: A block / disk based backup and restore solution
Home-page: http://backy2.com/
Author: Daniel Kraft <daniel.kraft@d9t.de>
Author-email: daniel.kraft@d9t.de
License: LGPL-3
Keywords: backup
Platform: UNKNOWN
Classifier: Development Status :: 4 - Beta
Classifier: Environment :: Console
Classifier: Intended Audience :: System Administrators
Classifier: License :: OSI Approved :: GNU Lesser General Public License v3 (LGPLv3)
Classifier: Operating System :: POSIX
Classifier: Programming Language :: Python
Classifier: Programming Language :: Python :: 3
Classifier: Programming Language :: Python :: 3.2
Classifier: Programming Language :: Python :: 3.3
Classifier: Programming Language :: Python :: 3.4
Classifier: Programming Language :: Python :: 3.5
Classifier: Programming Language :: Python :: 3.6
Classifier: Topic :: System :: Archiving :: Backup
